verdin/__init__.py
verdin/client.py
verdin/config.py
verdin/datasource.py
verdin/pipe.py
verdin/query.py
verdin/tinybird.py
verdin/worker.py
verdin/api/__init__.py
verdin/api/apis.py
verdin/api/base.py
verdin/api/datasources.py
verdin/api/events.py
verdin/api/pipes.py
verdin/api/query.py
verdin/api/tokens.py
verdin/api/variables.py
verdin/test/__init__.py
verdin/test/cli.py
verdin/test/container.py
verdin-0.5.2.dist-info/METADATA
verdin-0.5.2.dist-info/WHEEL
verdin-0.5.2.dist-info/licenses/LICENSE
verdin-0.5.2.dist-info/RECORD
