Metadata-Version: 2.4
Name: verdin
Version: 0.5.2
Summary: A Python SDK for Tinybird
Project-URL: Repository, https://github.com/localstack/verdin
Author-email: Thomas Rausch <info@localstack.cloud>
License-Expression: Apache-2.0
License-File: LICENSE
Classifier: Development Status :: 4 - Beta
Classifier: Operating System :: OS Independent
Classifier: Programming Language :: Python :: 3
Classifier: Programming Language :: Python :: 3.10
Classifier: Programming Language :: Python :: 3.11
Classifier: Programming Language :: Python :: 3.12
Classifier: Programming Language :: Python :: 3.13
Classifier: Topic :: Software Development :: Libraries
Classifier: Topic :: System :: Networking
Classifier: Topic :: Utilities
Requires-Python: >=3.10
Provides-Extra: dev
Requires-Dist: coverage[toml]>=5.0; extra == 'dev'
Requires-Dist: coveralls; extra == 'dev'
Requires-Dist: pytest-cov>=2.7.1; extra == 'dev'
Requires-Dist: pytest-httpserver>=1.0.1; extra == 'dev'
Requires-Dist: pytest>=6.2.4; extra == 'dev'
Requires-Dist: ruff==0.9.1; extra == 'dev'
Requires-Dist: tinybird; extra == 'dev'
